[
  {
    "name": "Theft - Other",
    "title": "Theft - Other",
    "requiredData": [
      {
        "name": "date",
        "title": "Date",
        "type": "DATE"
      },
      {
        "name": "place",
        "title": "Place",
        "type": "TEXT"
      },
      {
        "name": "item",
        "title": "Item",
        "type": "ASSET"
      }
    ],
    "optionalData": [
      {
        "name": "report",
        "title": "Police report",
        "type": "BOOL"
      },
      {
        "name": "receipt",
        "title": "Receipt",
        "type": "FILE"
      }
    ]
  },
    {
    "name": "Theft - Home",
    "title": "Theft - Home",
    "requiredData": [
      {
        "name": "date",
        "title": "Date",
        "type": "DATE"
      },
      {
        "name": "place",
        "title": "Place",
        "type": "TEXT"
      },
      {
        "name": "item",
        "title": "Item",
        "type": "ASSET"
      }
    ],
    "optionalData": [
      {
        "name": "report",
        "title": "Police report",
        "type": "BOOL"
      },
      {
        "name": "receipt",
        "title": "Receipt",
        "type": "FILE"
      }
    ]
  },
    {
    "name": "Theft - Bike",
    "title": "Theft - Bike",
    "requiredData": [
      {
        "name": "date",
        "title": "Date",
        "type": "DATE"
      },
      {
        "name": "place",
        "title": "Place",
        "type": "TEXT"
      },
      {
        "name": "item",
        "title": "Item",
        "type": "ASSET"
      }
    ],
    "optionalData": [
      {
        "name": "report",
        "title": "Police report",
        "type": "BOOL"
      },
      {
        "name": "receipt",
        "title": "Receipt",
        "type": "FILE"
      }
    ]
  },
    {
    "name": "Assault",
    "title": "Assault",
    "requiredData": [
      {
        "name": "date",
        "title": "Date",
        "type": "DATE"
      },
      {
        "name": "place",
        "title": "Place",
        "type": "TEXT"
      }
    ],
    "optionalData": [
      {
        "name": "report",
        "title": "Police report",
        "type": "BOOL"
      }
    ]
  },
    {
    "name": "Drulle - Mobile",
    "title": "Drulle - Mobile",
    "requiredData": [
      {
        "name": "date",
        "title": "Date",
        "type": "DATE"
      },
      {
        "name": "place",
        "title": "Place",
        "type": "TEXT"
      },
      {
        "name": "item",
        "title": "Item",
        "type": "ASSET"
      }
    ],
    "optionalData": [
      {
        "name": "report",
        "title": "Police report",
        "type": "BOOL"
      },
      {
        "name": "receipt",
        "title": "Receipt",
        "type": "FILE"
      }
    ]
  },
    {
    "name": "Drulle - Other",
    "title": "Drulle - Other",
    "requiredData": [
      {
        "name": "date",
        "title": "Date",
        "type": "DATE"
      },
      {
        "name": "place",
        "title": "Place",
        "type": "TEXT"
      },
      {
        "name": "item",
        "title": "Item",
        "type": "ASSET"
      }
    ],
    "optionalData": [
      {
        "name": "report",
        "title": "Police report",
        "type": "BOOL"
      },
      {
        "name": "receipt",
        "title": "Receipt",
        "type": "FILE"
      }
    ]
  },
    {
    "name": "Water damage - Kitchen",
    "title": "Water damage - Kitchen",
    "requiredData": [
      {
        "name": "date",
        "title": "Date",
        "type": "DATE"
      }
    ],
    "optionalData": [
    ]
  },
    {
    "name": "Water damage - Bathroom",
    "title": "Water damage - Bathroom",
    "requiredData": [
      {
        "name": "date",
        "title": "Date",
        "type": "DATE"
      }
    ],
    "optionalData": [

    ]
  },
    {
    "name": "Travel - Accident and Health",
    "title": "Travel - Accident and Health",
    "requiredData": [
      {
        "name": "date",
        "title": "Date",
        "type": "DATE"
      },
      {
        "name": "place",
        "title": "Place",
        "type": "TEXT"
      }
    ],
    "optionalData": [
      {
        "name": "report",
        "title": "Police report",
        "type": "BOOL"
      },
      {
        "name": "receipt",
        "title": "Receipt",
        "type": "FILE"
      }
    ]
  },
      {
    "name": "Travel - Delayed Luggage",
    "title": "Travel - Delayed Luggage",
    "requiredData": [
      {
        "name": "date",
        "title": "Date",
        "type": "DATE"
      },
      {
        "name": "place",
        "title": "Place",
        "type": "TEXT"
      }
    ],
    "optionalData": [
      {
        "name": "ticket",
        "title": "Ticket",
        "type": "BOOL"
      }
    ]
  }
]
